coolfig/__init__.py
coolfig/django.py
coolfig/providers.py
coolfig/schema.py
coolfig/types.py
coolfig/test/__init__.py
coolfig/test/test_config.py
coolfig/test/test_django.py
coolfig/test/test_providers.py
coolfig/test/test_schema.py
coolfig-3.1.0.dist-info/DESCRIPTION.rst
coolfig-3.1.0.dist-info/METADATA
coolfig-3.1.0.dist-info/RECORD
coolfig-3.1.0.dist-info/WHEEL
coolfig-3.1.0.dist-info/metadata.json
coolfig-3.1.0.dist-info/top_level.txt
