Metadata-Version: 1.1
Name: coolfig
Version: 3.1.0
Summary: Helpers for dealing with application settings
Home-page: https://github.com/GaretJax/coolfig
Author: Jonathan Stoppani
Author-email: jonathan@stoppani.name
License: MIT
Platform: UNKNOWN
Classifier: Development Status :: 4 - Beta
Classifier: Intended Audience :: Developers
Classifier: License :: OSI Approved :: MIT License
Classifier: Operating System :: OS Independent
Classifier: Programming Language :: Python
Classifier: Programming Language :: Python :: 2.7
Classifier: Programming Language :: Python :: 3
Classifier: Programming Language :: Python :: 3.3
Classifier: Programming Language :: Python :: 3.4
